azure/mgmt/apicenter/__init__.py
azure/mgmt/apicenter/_api_center_mgmt_client.py
azure/mgmt/apicenter/_configuration.py
azure/mgmt/apicenter/_patch.py
azure/mgmt/apicenter/_serialization.py
azure/mgmt/apicenter/_vendor.py
azure/mgmt/apicenter/_version.py
azure/mgmt/apicenter/py.typed
azure/mgmt/apicenter/aio/__init__.py
azure/mgmt/apicenter/aio/_api_center_mgmt_client.py
azure/mgmt/apicenter/aio/_configuration.py
azure/mgmt/apicenter/aio/_patch.py
azure/mgmt/apicenter/aio/operations/__init__.py
azure/mgmt/apicenter/aio/operations/_api_definitions_operations.py
azure/mgmt/apicenter/aio/operations/_api_versions_operations.py
azure/mgmt/apicenter/aio/operations/_apis_operations.py
azure/mgmt/apicenter/aio/operations/_deployments_operations.py
azure/mgmt/apicenter/aio/operations/_environments_operations.py
azure/mgmt/apicenter/aio/operations/_metadata_schemas_operations.py
azure/mgmt/apicenter/aio/operations/_operations.py
azure/mgmt/apicenter/aio/operations/_patch.py
azure/mgmt/apicenter/aio/operations/_services_operations.py
azure/mgmt/apicenter/aio/operations/_workspaces_operations.py
azure/mgmt/apicenter/models/__init__.py
azure/mgmt/apicenter/models/_api_center_mgmt_client_enums.py
azure/mgmt/apicenter/models/_models_py3.py
azure/mgmt/apicenter/models/_patch.py
azure/mgmt/apicenter/operations/__init__.py
azure/mgmt/apicenter/operations/_api_definitions_operations.py
azure/mgmt/apicenter/operations/_api_versions_operations.py
azure/mgmt/apicenter/operations/_apis_operations.py
azure/mgmt/apicenter/operations/_deployments_operations.py
azure/mgmt/apicenter/operations/_environments_operations.py
azure/mgmt/apicenter/operations/_metadata_schemas_operations.py
azure/mgmt/apicenter/operations/_operations.py
azure/mgmt/apicenter/operations/_patch.py
azure/mgmt/apicenter/operations/_services_operations.py
azure/mgmt/apicenter/operations/_workspaces_operations.py
azure_mgmt_apicenter-1.0.0.dist-info/LICENSE
azure_mgmt_apicenter-1.0.0.dist-info/METADATA
azure_mgmt_apicenter-1.0.0.dist-info/WHEEL
azure_mgmt_apicenter-1.0.0.dist-info/top_level.txt
azure_mgmt_apicenter-1.0.0.dist-info/RECORD
